slack_blocks_wrapper/__init__.py
slack_blocks_wrapper/context.py
slack_blocks_wrapper/divider.py
slack_blocks_wrapper/file.py
slack_blocks_wrapper/header.py
slack_blocks_wrapper/image.py
slack_blocks_wrapper/input.py
slack_blocks_wrapper/elements/__init__.py
slack_blocks_wrapper/elements/button.py
slack_blocks_wrapper/elements/checkbox.py
slack_blocks_wrapper/elements/datepicker.py
slack_blocks_wrapper/elements/image.py
slack_blocks_wrapper/elements/multiselect.py
slack_blocks_wrapper/elements/overflow_menu.py
slack_blocks_wrapper/elements/plain_text_input.py
slack_blocks_wrapper/elements/radio_button.py
slack_blocks_wrapper/elements/select.py
slack_blocks_wrapper/elements/text.py
slack_blocks_wrapper/elements/timepicker.py
slack_blocks_wrapper/section/__init__.py
slack_blocks_wrapper/section/section_elements.py
slack_blocks_wrapper-0.2.6.dist-info/LICENSE.md
slack_blocks_wrapper-0.2.6.dist-info/METADATA
slack_blocks_wrapper-0.2.6.dist-info/WHEEL
slack_blocks_wrapper-0.2.6.dist-info/top_level.txt
slack_blocks_wrapper-0.2.6.dist-info/RECORD
