Metadata-Version: 2.1
Name: slack-blocks-wrapper
Version: 0.2.6
Summary: A python3 wrapper for the slack block kit framework
Home-page: https://github.com/AllanPy/slack-blocks-wrapper
Author: Allan Mogusu
Author-email: allannelly690@gmail.com
License: MIT
Platform: UNKNOWN
Classifier: License :: OSI Approved :: MIT License
Classifier: Programming Language :: Python :: 3
Classifier: Programming Language :: Python :: 3.7
